django_libsass.py
django_libsass-0.8.dist-info/LICENSE
django_libsass-0.8.dist-info/METADATA
django_libsass-0.8.dist-info/WHEEL
django_libsass-0.8.dist-info/top_level.txt
django_libsass-0.8.dist-info/RECORD
